<annotation>
	<folder>train</folder>
	<filename>low (46).jpg</filename>
	<path>C:\bsu_thesis\Tensorflow\workspace\images\train\low (46).jpg</path>
	<source>
		<database>Unknown</database>
	</source>
	<size>
		<width>1685</width>
		<height>1230</height>
		<depth>3</depth>
	</size>
	<segmented>0</segmented>
	<object>
		<name>LRCI_healthy</name>
		<pose>Unspecified</pose>
		<truncated>0</truncated>
		<difficult>0</difficult>
		<bndbox>
			<xmin>700</xmin>
			<ymin>991</ymin>
			<xmax>839</xmax>
			<ymax>1161</ymax>
		</bndbox>
	</object>
	<object>
		<name>LRLI_healthy</name>
		<pose>Unspecified</pose>
		<truncated>0</truncated>
		<difficult>0</difficult>
		<bndbox>
			<xmin>545</xmin>
			<ymin>961</ymin>
			<xmax>727</xmax>
			<ymax>1132</ymax>
		</bndbox>
	</object>
	<object>
		<name>LRC_healthy</name>
		<pose>Unspecified</pose>
		<truncated>0</truncated>
		<difficult>0</difficult>
		<bndbox>
			<xmin>429</xmin>
			<ymin>883</ymin>
			<xmax>572</xmax>
			<ymax>1075</ymax>
		</bndbox>
	</object>
	<object>
		<name>LR1BC_healthy</name>
		<pose>Unspecified</pose>
		<truncated>0</truncated>
		<difficult>0</difficult>
		<bndbox>
			<xmin>303</xmin>
			<ymin>723</ymin>
			<xmax>495</xmax>
			<ymax>941</ymax>
		</bndbox>
	</object>
	<object>
		<name>LR2BC_decay</name>
		<pose>Unspecified</pose>
		<truncated>0</truncated>
		<difficult>0</difficult>
		<bndbox>
			<xmin>236</xmin>
			<ymin>559</ymin>
			<xmax>456</xmax>
			<ymax>801</ymax>
		</bndbox>
	</object>
	<object>
		<name>LR1M_decay</name>
		<pose>Unspecified</pose>
		<truncated>0</truncated>
		<difficult>0</difficult>
		<bndbox>
			<xmin>103</xmin>
			<ymin>327</ymin>
			<xmax>403</xmax>
			<ymax>617</ymax>
		</bndbox>
	</object>
	<object>
		<name>LR2M_decay</name>
		<pose>Unspecified</pose>
		<truncated>0</truncated>
		<difficult>0</difficult>
		<bndbox>
			<xmin>59</xmin>
			<ymin>80</ymin>
			<xmax>320</xmax>
			<ymax>364</ymax>
		</bndbox>
	</object>
	<object>
		<name>LLCI_healthy</name>
		<pose>Unspecified</pose>
		<truncated>0</truncated>
		<difficult>0</difficult>
		<bndbox>
			<xmin>828</xmin>
			<ymin>991</ymin>
			<xmax>983</xmax>
			<ymax>1169</ymax>
		</bndbox>
	</object>
	<object>
		<name>LLLI_healthy</name>
		<pose>Unspecified</pose>
		<truncated>0</truncated>
		<difficult>0</difficult>
		<bndbox>
			<xmin>967</xmin>
			<ymin>959</ymin>
			<xmax>1116</xmax>
			<ymax>1159</ymax>
		</bndbox>
	</object>
	<object>
		<name>LLC_healthy</name>
		<pose>Unspecified</pose>
		<truncated>0</truncated>
		<difficult>0</difficult>
		<bndbox>
			<xmin>1089</xmin>
			<ymin>877</ymin>
			<xmax>1249</xmax>
			<ymax>1081</ymax>
		</bndbox>
	</object>
	<object>
		<name>LL1BC_healthy</name>
		<pose>Unspecified</pose>
		<truncated>0</truncated>
		<difficult>0</difficult>
		<bndbox>
			<xmin>1153</xmin>
			<ymin>748</ymin>
			<xmax>1364</xmax>
			<ymax>972</ymax>
		</bndbox>
	</object>
	<object>
		<name>LL2BC_decay</name>
		<pose>Unspecified</pose>
		<truncated>0</truncated>
		<difficult>0</difficult>
		<bndbox>
			<xmin>1224</xmin>
			<ymin>595</ymin>
			<xmax>1443</xmax>
			<ymax>803</ymax>
		</bndbox>
	</object>
	<object>
		<name>LL1M_decay</name>
		<pose>Unspecified</pose>
		<truncated>0</truncated>
		<difficult>0</difficult>
		<bndbox>
			<xmin>1259</xmin>
			<ymin>345</ymin>
			<xmax>1556</xmax>
			<ymax>631</ymax>
		</bndbox>
	</object>
	<object>
		<name>LL2M_decay</name>
		<pose>Unspecified</pose>
		<truncated>0</truncated>
		<difficult>0</difficult>
		<bndbox>
			<xmin>1340</xmin>
			<ymin>117</ymin>
			<xmax>1632</xmax>
			<ymax>381</ymax>
		</bndbox>
	</object>
</annotation>
