<annotation>
	<folder>dann_up_242-361</folder>
	<filename>up (314).jpg</filename>
	<path>D:\bsu_thesis\Tensorflow\workspace\images\train\dann_up_242-361\up (314).jpg</path>
	<source>
		<database>Unknown</database>
	</source>
	<size>
		<width>1200</width>
		<height>1200</height>
		<depth>3</depth>
	</size>
	<segmented>0</segmented>
	<object>
		<name>URCI_healthy</name>
		<pose>Unspecified</pose>
		<truncated>0</truncated>
		<difficult>0</difficult>
		<bndbox>
			<xmin>440</xmin>
			<ymin>103</ymin>
			<xmax>604</xmax>
			<ymax>263</ymax>
		</bndbox>
	</object>
	<object>
		<name>URLI_healthy</name>
		<pose>Unspecified</pose>
		<truncated>0</truncated>
		<difficult>0</difficult>
		<bndbox>
			<xmin>322</xmin>
			<ymin>148</ymin>
			<xmax>458</xmax>
			<ymax>290</ymax>
		</bndbox>
	</object>
	<object>
		<name>URC_healthy</name>
		<pose>Unspecified</pose>
		<truncated>0</truncated>
		<difficult>0</difficult>
		<bndbox>
			<xmin>211</xmin>
			<ymin>230</ymin>
			<xmax>379</xmax>
			<ymax>403</ymax>
		</bndbox>
	</object>
	<object>
		<name>UR1BC_healthy</name>
		<pose>Unspecified</pose>
		<truncated>0</truncated>
		<difficult>0</difficult>
		<bndbox>
			<xmin>141</xmin>
			<ymin>381</ymin>
			<xmax>314</xmax>
			<ymax>537</ymax>
		</bndbox>
	</object>
	<object>
		<name>UR2BC_healthy</name>
		<pose>Unspecified</pose>
		<truncated>0</truncated>
		<difficult>0</difficult>
		<bndbox>
			<xmin>98</xmin>
			<ymin>533</ymin>
			<xmax>285</xmax>
			<ymax>669</ymax>
		</bndbox>
	</object>
	<object>
		<name>UR1M_healthy</name>
		<pose>Unspecified</pose>
		<truncated>0</truncated>
		<difficult>0</difficult>
		<bndbox>
			<xmin>14</xmin>
			<ymin>634</ymin>
			<xmax>226</xmax>
			<ymax>863</ymax>
		</bndbox>
	</object>
	<object>
		<name>UR2M_healthy</name>
		<pose>Unspecified</pose>
		<truncated>0</truncated>
		<difficult>0</difficult>
		<bndbox>
			<xmin>35</xmin>
			<ymin>840</ymin>
			<xmax>191</xmax>
			<ymax>1000</ymax>
		</bndbox>
	</object>
	<object>
		<name>ULCI_healthy</name>
		<pose>Unspecified</pose>
		<truncated>0</truncated>
		<difficult>0</difficult>
		<bndbox>
			<xmin>608</xmin>
			<ymin>110</ymin>
			<xmax>767</xmax>
			<ymax>266</ymax>
		</bndbox>
	</object>
	<object>
		<name>ULLI_healthy</name>
		<pose>Unspecified</pose>
		<truncated>0</truncated>
		<difficult>0</difficult>
		<bndbox>
			<xmin>757</xmin>
			<ymin>165</ymin>
			<xmax>885</xmax>
			<ymax>309</ymax>
		</bndbox>
	</object>
	<object>
		<name>ULC_healthy</name>
		<pose>Unspecified</pose>
		<truncated>0</truncated>
		<difficult>0</difficult>
		<bndbox>
			<xmin>819</xmin>
			<ymin>253</ymin>
			<xmax>981</xmax>
			<ymax>419</ymax>
		</bndbox>
	</object>
	<object>
		<name>UL1BC_healthy</name>
		<pose>Unspecified</pose>
		<truncated>0</truncated>
		<difficult>0</difficult>
		<bndbox>
			<xmin>863</xmin>
			<ymin>403</ymin>
			<xmax>1040</xmax>
			<ymax>554</ymax>
		</bndbox>
	</object>
	<object>
		<name>UL2BC_healthy</name>
		<pose>Unspecified</pose>
		<truncated>0</truncated>
		<difficult>0</difficult>
		<bndbox>
			<xmin>893</xmin>
			<ymin>542</ymin>
			<xmax>1090</xmax>
			<ymax>696</ymax>
		</bndbox>
	</object>
	<object>
		<name>UL1M_healthy</name>
		<pose>Unspecified</pose>
		<truncated>0</truncated>
		<difficult>0</difficult>
		<bndbox>
			<xmin>917</xmin>
			<ymin>686</ymin>
			<xmax>1125</xmax>
			<ymax>916</ymax>
		</bndbox>
	</object>
	<object>
		<name>UL2M_decay</name>
		<pose>Unspecified</pose>
		<truncated>0</truncated>
		<difficult>0</difficult>
		<bndbox>
			<xmin>985</xmin>
			<ymin>918</ymin>
			<xmax>1163</xmax>
			<ymax>1000</ymax>
		</bndbox>
	</object>
</annotation>
