<annotation>
	<folder>dann_up_242-361</folder>
	<filename>up (302).jpg</filename>
	<path>D:\bsu_thesis\Tensorflow\workspace\images\train\dann_up_242-361\up (302).jpg</path>
	<source>
		<database>Unknown</database>
	</source>
	<size>
		<width>1080</width>
		<height>540</height>
		<depth>3</depth>
	</size>
	<segmented>0</segmented>
	<object>
		<name>URCI_decay</name>
		<pose>Unspecified</pose>
		<truncated>0</truncated>
		<difficult>0</difficult>
		<bndbox>
			<xmin>452</xmin>
			<ymin>54</ymin>
			<xmax>559</xmax>
			<ymax>147</ymax>
		</bndbox>
	</object>
	<object>
		<name>URLI_decay</name>
		<pose>Unspecified</pose>
		<truncated>0</truncated>
		<difficult>0</difficult>
		<bndbox>
			<xmin>365</xmin>
			<ymin>85</ymin>
			<xmax>453</xmax>
			<ymax>172</ymax>
		</bndbox>
	</object>
	<object>
		<name>URC_decay</name>
		<pose>Unspecified</pose>
		<truncated>0</truncated>
		<difficult>0</difficult>
		<bndbox>
			<xmin>296</xmin>
			<ymin>140</ymin>
			<xmax>389</xmax>
			<ymax>233</ymax>
		</bndbox>
	</object>
	<object>
		<name>UR1BC_healthy</name>
		<pose>Unspecified</pose>
		<truncated>0</truncated>
		<difficult>0</difficult>
		<bndbox>
			<xmin>246</xmin>
			<ymin>230</ymin>
			<xmax>358</xmax>
			<ymax>330</ymax>
		</bndbox>
	</object>
	<object>
		<name>UR2BC_healthy</name>
		<pose>Unspecified</pose>
		<truncated>0</truncated>
		<difficult>0</difficult>
		<bndbox>
			<xmin>194</xmin>
			<ymin>316</ymin>
			<xmax>329</xmax>
			<ymax>469</ymax>
		</bndbox>
	</object>
	<object>
		<name>UR1M_healthy</name>
		<pose>Unspecified</pose>
		<truncated>0</truncated>
		<difficult>0</difficult>
		<bndbox>
			<xmin>156</xmin>
			<ymin>443</ymin>
			<xmax>280</xmax>
			<ymax>538</ymax>
		</bndbox>
	</object>
	<object>
		<name>ULCI_decay</name>
		<pose>Unspecified</pose>
		<truncated>0</truncated>
		<difficult>0</difficult>
		<bndbox>
			<xmin>558</xmin>
			<ymin>56</ymin>
			<xmax>669</xmax>
			<ymax>153</ymax>
		</bndbox>
	</object>
	<object>
		<name>ULLI_decay</name>
		<pose>Unspecified</pose>
		<truncated>0</truncated>
		<difficult>0</difficult>
		<bndbox>
			<xmin>666</xmin>
			<ymin>84</ymin>
			<xmax>753</xmax>
			<ymax>178</ymax>
		</bndbox>
	</object>
	<object>
		<name>ULC_healthy</name>
		<pose>Unspecified</pose>
		<truncated>0</truncated>
		<difficult>0</difficult>
		<bndbox>
			<xmin>733</xmin>
			<ymin>146</ymin>
			<xmax>819</xmax>
			<ymax>240</ymax>
		</bndbox>
	</object>
	<object>
		<name>UL1BC_healthy</name>
		<pose>Unspecified</pose>
		<truncated>0</truncated>
		<difficult>0</difficult>
		<bndbox>
			<xmin>749</xmin>
			<ymin>236</ymin>
			<xmax>853</xmax>
			<ymax>328</ymax>
		</bndbox>
	</object>
	<object>
		<name>UL2BC_healthy</name>
		<pose>Unspecified</pose>
		<truncated>0</truncated>
		<difficult>0</difficult>
		<bndbox>
			<xmin>762</xmin>
			<ymin>313</ymin>
			<xmax>894</xmax>
			<ymax>460</ymax>
		</bndbox>
	</object>
	<object>
		<name>UL1M_healthy</name>
		<pose>Unspecified</pose>
		<truncated>1</truncated>
		<difficult>0</difficult>
		<bndbox>
			<xmin>806</xmin>
			<ymin>435</ymin>
			<xmax>917</xmax>
			<ymax>540</ymax>
		</bndbox>
	</object>
</annotation>
